[
    {
        "key": "dbln",
        "value": "%7B%2261571081680426%22%3A%22jqHTHUa7%22%2C%22100000172070710%22%3A%22u2iBnmP9%22%7D",
        "domain": "facebook.com",
        "path": "/login/device-based/",
        "hostOnly": false,
        "creation": "2025-08-13T17:53:39.245Z",
        "lastAccessed": "2025-08-13T17:53:39.245Z"
    },
    {
        "key": "vpd",
        "value": "v1%3B755x400x1.8000000715255737",
        "domain": "facebook.com",
        "path": "/",
        "hostOnly": false,
        "creation": "2025-08-13T17:53:39.245Z",
        "lastAccessed": "2025-08-13T17:53:39.245Z"
    },
    {
        "key": "datr",
        "value": "8FacaGkFTzHYvNrp8io8V2mz",
        "domain": "facebook.com",
        "path": "/",
        "hostOnly": false,
        "creation": "2025-08-13T17:53:39.245Z",
        "lastAccessed": "2025-08-13T17:53:39.245Z"
    },
    {
        "key": "sb",
        "value": "8FacaOPKTbOy8Fd43e2IiIB6",
        "domain": "facebook.com",
        "path": "/",
        "hostOnly": false,
        "creation": "2025-08-13T17:53:39.245Z",
        "lastAccessed": "2025-08-13T17:53:39.245Z"
    },
    {
        "key": "m_pixel_ratio",
        "value": "1.8000000715255737",
        "domain": "facebook.com",
        "path": "/",
        "hostOnly": false,
        "creation": "2025-08-13T17:53:39.245Z",
        "lastAccessed": "2025-08-13T17:53:39.245Z"
    },
    {
        "key": "wd",
        "value": "400x896",
        "domain": "facebook.com",
        "path": "/",
        "hostOnly": false,
        "creation": "2025-08-13T17:53:39.245Z",
        "lastAccessed": "2025-08-13T17:53:39.245Z"
    },
    {
        "key": "ps_l",
        "value": "1",
        "domain": "facebook.com",
        "path": "/",
        "hostOnly": false,
        "creation": "2025-08-13T17:53:39.245Z",
        "lastAccessed": "2025-08-13T17:53:39.245Z"
    },
    {
        "key": "ps_n",
        "value": "1",
        "domain": "facebook.com",
        "path": "/",
        "hostOnly": false,
        "creation": "2025-08-13T17:53:39.245Z",
        "lastAccessed": "2025-08-13T17:53:39.245Z"
    },
    {
        "key": "c_user",
        "value": "100000172070710",
        "domain": "facebook.com",
        "path": "/",
        "hostOnly": false,
        "creation": "2025-08-13T17:53:39.245Z",
        "lastAccessed": "2025-08-13T17:53:39.245Z"
    },
    {
        "key": "xs",
        "value": "26%3Aq9C0Y_lQay8khw%3A2%3A1755107601%3A-1%3A-1",
        "domain": "facebook.com",
        "path": "/",
        "hostOnly": false,
        "creation": "2025-08-13T17:53:39.245Z",
        "lastAccessed": "2025-08-13T17:53:39.245Z"
    },
    {
        "key": "fr",
        "value": "0lWFl8ztqBP8uD1BI.AWcOl3wiQvuDn_S5qDJODyCmEp8N4I26DgCHLXPrP3GyOnxXcys.BolgVG..AAA.0.0.BonNEY.AWeXOJdvGtO8ub-T2XOjMgEDdQM",
        "domain": "facebook.com",
        "path": "/",
        "hostOnly": false,
        "creation": "2025-08-13T17:53:39.245Z",
        "lastAccessed": "2025-08-13T17:53:39.245Z"
    },
    {
        "key": "locale",
        "value": "en_US",
        "domain": "facebook.com",
        "path": "/",
        "hostOnly": false,
        "creation": "2025-08-13T17:53:39.245Z",
        "lastAccessed": "2025-08-13T17:53:39.245Z"
    },
    {
        "key": "pas",
        "value": "61571081680426%3AlSmdo6OlGG%2C100000172070710%3AbH9xq2gEC7%2C100090104133064%3AQzPAm9sES8",
        "domain": "facebook.com",
        "path": "/",
        "hostOnly": false,
        "creation": "2025-08-13T17:53:39.245Z",
        "lastAccessed": "2025-08-13T17:53:39.245Z"
    },
    {
        "key": "fbl_st",
        "value": "101536108%3BT%3A29251793",
        "domain": "facebook.com",
        "path": "/",
        "hostOnly": false,
        "creation": "2025-08-13T17:53:39.245Z",
        "lastAccessed": "2025-08-13T17:53:39.245Z"
    },
    {
        "key": "wl_cbv",
        "value": "v2%3Bclient_version%3A2891%3Btimestamp%3A1755107608",
        "domain": "facebook.com",
        "path": "/",
        "hostOnly": false,
        "creation": "2025-08-13T17:53:39.245Z",
        "lastAccessed": "2025-08-13T17:53:39.245Z"
    }
]

